senginta/tests.py
senginta/static/search.py
senginta/static/Baidu/__init__.py
senginta/static/Baidu/baidu_search.py
senginta/static/Baidu/settings.py
senginta/static/Google/__init__.py
senginta/static/Google/google_books.py
senginta/static/Google/google_news.py
senginta/static/Google/google_scholar.py
senginta/static/Google/google_search.py
senginta/static/Google/google_shop.py
senginta/static/Google/google_video.py
senginta/static/Google/settings.py
senginta-0.0.3.0.dist-info/LICENSE
senginta-0.0.3.0.dist-info/METADATA
senginta-0.0.3.0.dist-info/WHEEL
senginta-0.0.3.0.dist-info/top_level.txt
senginta-0.0.3.0.dist-info/RECORD
