Metadata-Version: 2.1
Name: senginta
Version: 0.0.3.0
Summary: All in one Search Engine for used by API or Python Module (Unofficial)
Home-page: UNKNOWN
Author: Michael Abraham Chan Tulenan
Author-email: michael.4ct@gmail.com
License: UNKNOWN
Platform: UNKNOWN
Classifier: Programming Language :: Python :: 3
Classifier: License :: OSI Approved :: MIT License
Classifier: Operating System :: OS Independent
Requires-Python: >=3.8
Requires-Dist: beautifulsoup4
Requires-Dist: pandas
Requires-Dist: requests
Requires-Dist: urllib3
